imagen_ai_sdk-1.0.1.dist-info/licenses/LICENSE
imagen_sdk/__init__.py
imagen_sdk/enums.py
imagen_sdk/exceptions.py
imagen_sdk/imagen_sdk.py
imagen_sdk/models.py
imagen_ai_sdk-1.0.1.dist-info/METADATA
imagen_ai_sdk-1.0.1.dist-info/WHEEL
imagen_ai_sdk-1.0.1.dist-info/top_level.txt
imagen_ai_sdk-1.0.1.dist-info/RECORD
