Metadata-Version: 2.4
Name: imagen-ai-sdk
Version: 1.0.1
Summary: A robust, Pydantic-powered SDK for the Imagen AI photo editing workflow
Author-email: Shahar Polak <shahar@imagen-ai.com>
License: MIT
Project-URL: Homepage, https://github.com/imagenai/imagen-ai-sdk
Project-URL: Documentation, https://support.imagen-ai.com/hc/en-us/articles/19137253415965-Automate-your-post-production-workflow-with-Imagen-API
Project-URL: Repository, https://github.com/imagenai/imagen-ai-sdk
Project-URL: Bug Reports, https://github.com/imagenai/imagen-ai-sdk/issues
Keywords: imagen,ai,photo,editing,automation,photography
Classifier: Development Status :: 4 - Beta
Classifier: Intended Audience :: Developers
Classifier: Programming Language :: Python :: 3
Classifier: Programming Language :: Python :: 3.7
Classifier: Programming Language :: Python :: 3.8
Classifier: Programming Language :: Python :: 3.9
Classifier: Programming Language :: Python :: 3.10
Classifier: Programming Language :: Python :: 3.11
Classifier: Programming Language :: Python :: 3.12
Classifier: Topic :: Software Development :: Libraries :: Python Modules
Classifier: Topic :: Multimedia :: Graphics :: Graphics Conversion
Requires-Python: >=3.7
License-File: LICENSE
Requires-Dist: httpx>=0.24.0
Requires-Dist: aiofiles>=23.0.0
Requires-Dist: pydantic>=2.0.0
Provides-Extra: dev
Requires-Dist: pytest>=7.0; extra == "dev"
Requires-Dist: pytest-cov>=4.0; extra == "dev"
Requires-Dist: pytest-asyncio>=0.21.0; extra == "dev"
Requires-Dist: pytest-mock>=3.10.0; extra == "dev"
Requires-Dist: black>=21.0; extra == "dev"
Requires-Dist: mypy>=0.800; extra == "dev"
Requires-Dist: pre-commit>=3.0; extra == "dev"
Requires-Dist: ruff>=0.4.8; extra == "dev"
Provides-Extra: test
Requires-Dist: pytest>=7.0; extra == "test"
Requires-Dist: pytest-cov>=4.0; extra == "test"
Requires-Dist: pytest-asyncio>=0.21.0; extra == "test"
Requires-Dist: pytest-mock>=3.10.0; extra == "test"
Requires-Dist: black>=21.0; extra == "test"
Requires-Dist: flake8>=3.8; extra == "test"
Requires-Dist: mypy>=0.800; extra == "test"
Dynamic: license-file
